qa_generator/__init__.py
qa_generator/config.py
qa_generator/dataset_generator.py
qa_generator/generator.py
qa_generator/llm_generator.py
qa_generator/preprocessor.py
qa_generator-0.1.0.dist-info/METADATA
qa_generator-0.1.0.dist-info/WHEEL
qa_generator-0.1.0.dist-info/top_level.txt
qa_generator-0.1.0.dist-info/RECORD
