Metadata-Version: 2.4
Name: qa-generator
Version: 0.1.0
Summary: A Python package to generate question-answer pairs from plain text
Home-page: https://github.com/hemanth/qa-generator
Author: QA Generator Team
Author-email: 
License: MIT
Project-URL: Homepage, https://github.com/hemanth/qa-generator
Project-URL: Repository, https://github.com/hemanth/qa-generator
Classifier: Development Status :: 3 - Alpha
Classifier: Intended Audience :: Developers
Classifier: License :: OSI Approved :: MIT License
Classifier: Operating System :: OS Independent
Classifier: Programming Language :: Python :: 3
Classifier: Programming Language :: Python :: 3.8
Classifier: Programming Language :: Python :: 3.9
Classifier: Programming Language :: Python :: 3.10
Classifier: Programming Language :: Python :: 3.11
Requires-Python: >=3.8
Requires-Dist: nltk>=3.8
Requires-Dist: requests>=2.25.0
Provides-Extra: dev
Requires-Dist: pytest>=7.0.0; extra == "dev"
Requires-Dist: black>=22.0.0; extra == "dev"
Requires-Dist: flake8>=4.0.0; extra == "dev"
Provides-Extra: llm
Requires-Dist: transformers>=4.20.0; extra == "llm"
Requires-Dist: torch>=1.12.0; extra == "llm"
Provides-Extra: datasets
Requires-Dist: pandas>=1.3.0; extra == "datasets"
Requires-Dist: datasets>=2.0.0; extra == "datasets"
Requires-Dist: huggingface_hub>=0.10.0; extra == "datasets"
Provides-Extra: advanced
Requires-Dist: spacy>=3.4.0; extra == "advanced"
Provides-Extra: all
Requires-Dist: transformers>=4.20.0; extra == "all"
Requires-Dist: torch>=1.12.0; extra == "all"
Requires-Dist: pandas>=1.3.0; extra == "all"
Requires-Dist: datasets>=2.0.0; extra == "all"
Requires-Dist: huggingface_hub>=0.10.0; extra == "all"
Requires-Dist: spacy>=3.4.0; extra == "all"
Dynamic: home-page
Dynamic: requires-python
